pyperbox.py
pyperbox-0.1.1.dist-info/LICENSE
pyperbox-0.1.1.dist-info/METADATA
pyperbox-0.1.1.dist-info/WHEEL
pyperbox-0.1.1.dist-info/RECORD
