Metadata-Version: 2.3
Name: pyperbox
Version: 0.1.1
Summary: Python implementation of a hyperbox
License: MIT
Author: vitroid
Author-email: vitroid@gmail.com
Requires-Python: >=3.11
Classifier: License :: OSI Approved :: MIT License
Classifier: Programming Language :: Python :: 3
Classifier: Programming Language :: Python :: 3.11
Classifier: Programming Language :: Python :: 3.12
Classifier: Programming Language :: Python :: 3.13
Requires-Dist: deprecation (>=2.1.0,<3.0.0)
